printserver/__init__.py
printserver/__main__.py
printserver/domains.py
printserver/index.py
printserver/print_job.py
printserver/printers.py
printserver/print_systems/__init__.py
printserver/print_systems/base.py
printserver/print_systems/brother_ql.py
printserver/print_systems/cups.py
printserver-2.4.5.dist-info/METADATA
printserver-2.4.5.dist-info/WHEEL
printserver-2.4.5.dist-info/entry_points.txt
printserver-2.4.5.dist-info/licenses/LICENSE
printserver-2.4.5.dist-info/RECORD
